README.md
recorder.py
setup.py
recorder.egg-info/PKG-INFO
recorder.egg-info/SOURCES.txt
recorder.egg-info/dependency_links.txt
recorder.egg-info/requires.txt
recorder.egg-info/top_level.txt