Metadata-Version: 2.1
Name: recorder
Version: 0.0.2
Summary: a simple audio recorder
Home-page: https://github.com/lixk/recorder
Author: Xiangkui Li
Author-email: 1749498702@qq.com
License: MIT Licence
Keywords: pip,recorder
Platform: any
